mujoco_py/__init__.py
mujoco_py/binaries/linux/mujoco210/THIRD_PARTY_NOTICES
mujoco_py/binaries/linux/mujoco210/bin/basic
mujoco_py/binaries/linux/mujoco210/bin/compile
mujoco_py/binaries/linux/mujoco210/bin/derivative
mujoco_py/binaries/linux/mujoco210/bin/libglew.so
mujoco_py/binaries/linux/mujoco210/bin/libglewegl.so
mujoco_py/binaries/linux/mujoco210/bin/libglewosmesa.so
mujoco_py/binaries/linux/mujoco210/bin/libglfw.so.3
mujoco_py/binaries/linux/mujoco210/bin/libglfw3.a
mujoco_py/binaries/linux/mujoco210/bin/libmujoco210.so
mujoco_py/binaries/linux/mujoco210/bin/libmujoco210nogl.so
mujoco_py/binaries/linux/mujoco210/bin/record
mujoco_py/binaries/linux/mujoco210/bin/simulate
mujoco_py/binaries/linux/mujoco210/bin/testspeed
mujoco_py/binaries/linux/mujoco210/bin/testxml
mujoco_py/binaries/linux/mujoco210/include/glfw3.h
mujoco_py/binaries/linux/mujoco210/include/mjdata.h
mujoco_py/binaries/linux/mujoco210/include/mjmodel.h
mujoco_py/binaries/linux/mujoco210/include/mjrender.h
mujoco_py/binaries/linux/mujoco210/include/mjui.h
mujoco_py/binaries/linux/mujoco210/include/mjvisualize.h
mujoco_py/binaries/linux/mujoco210/include/mjxmacro.h
mujoco_py/binaries/linux/mujoco210/include/mujoco.h
mujoco_py/binaries/linux/mujoco210/include/uitools.c
mujoco_py/binaries/linux/mujoco210/include/uitools.h
mujoco_py/binaries/linux/mujoco210/model/arm26.xml
mujoco_py/binaries/linux/mujoco210/model/carpet.png
mujoco_py/binaries/linux/mujoco210/model/cloth.xml
mujoco_py/binaries/linux/mujoco210/model/grid1.xml
mujoco_py/binaries/linux/mujoco210/model/grid1pin.xml
mujoco_py/binaries/linux/mujoco210/model/grid2.xml
mujoco_py/binaries/linux/mujoco210/model/grid2pin.xml
mujoco_py/binaries/linux/mujoco210/model/hammock.xml
mujoco_py/binaries/linux/mujoco210/model/humanoid.xml
mujoco_py/binaries/linux/mujoco210/model/humanoid100.xml
mujoco_py/binaries/linux/mujoco210/model/loop.xml
mujoco_py/binaries/linux/mujoco210/model/marble.png
mujoco_py/binaries/linux/mujoco210/model/particle.xml
free_mujoco_py-2.1.6.dist-info/LICENSE.md
free_mujoco_py-2.1.6.dist-info/WHEEL
free_mujoco_py-2.1.6.dist-info/METADATA
free_mujoco_py-2.1.6.dist-info/RECORD
