Metadata-Version: 2.1
Name: free-mujoco-py
Version: 2.1.6
Summary: 
Author: Costa Huang
Author-email: costa.huang@outlook.com
Requires-Python: >=3.7.1,<3.11
Classifier: Programming Language :: Python :: 3
Classifier: Programming Language :: Python :: 3.10
Classifier: Programming Language :: Python :: 3.8
Classifier: Programming Language :: Python :: 3.9
Requires-Dist: Cython (>=0.29.24,<0.30.0)
Requires-Dist: cffi (>=1.15.0,<2.0.0)
Requires-Dist: fasteners (==0.15)
Requires-Dist: glfw (>=1.4.0,<2.0.0)
Requires-Dist: imageio (>=2.9.0,<3.0.0)
Requires-Dist: numpy (>=1.21.3,<2.0.0)
